odoo/addons/account_bank_statement_import_online_transferwise/README.rst
odoo/addons/account_bank_statement_import_online_transferwise/__init__.py
odoo/addons/account_bank_statement_import_online_transferwise/__manifest__.py
odoo/addons/account_bank_statement_import_online_transferwise/i18n/account_bank_statement_import_online_transferwise.pot
odoo/addons/account_bank_statement_import_online_transferwise/models/__init__.py
odoo/addons/account_bank_statement_import_online_transferwise/models/online_bank_statement_provider_transferwise.py
odoo/addons/account_bank_statement_import_online_transferwise/readme/CONFIGURE.rst
odoo/addons/account_bank_statement_import_online_transferwise/readme/CONTRIBUTORS.rst
odoo/addons/account_bank_statement_import_online_transferwise/readme/DESCRIPTION.rst
odoo/addons/account_bank_statement_import_online_transferwise/readme/USAGE.rst
odoo/addons/account_bank_statement_import_online_transferwise/static/description/icon.png
odoo/addons/account_bank_statement_import_online_transferwise/static/description/index.html
odoo/addons/account_bank_statement_import_online_transferwise/tests/__init__.py
odoo/addons/account_bank_statement_import_online_transferwise/tests/test_account_bank_statement_import_online_transferwise.py
odoo/addons/account_bank_statement_import_online_transferwise/views/online_bank_statement_provider.xml
odoo11_addon_account_bank_statement_import_online_transferwise-11.0.1.1.0.dist-info/METADATA
odoo11_addon_account_bank_statement_import_online_transferwise-11.0.1.1.0.dist-info/WHEEL
odoo11_addon_account_bank_statement_import_online_transferwise-11.0.1.1.0.dist-info/top_level.txt
odoo11_addon_account_bank_statement_import_online_transferwise-11.0.1.1.0.dist-info/RECORD
